band_analyzer/EG_analysis.py
band_analyzer/__init__.py
band_analyzer-0.1.dist-info/METADATA
band_analyzer-0.1.dist-info/WHEEL
band_analyzer-0.1.dist-info/top_level.txt
band_analyzer-0.1.dist-info/RECORD
